{
  "$type": "Brasserie.Model.Restaurant.People.StaffMembersCollection, Brasserie",
  "$values": [
    {
      "$type": "Brasserie.Model.Restaurant.People.StaffMember, Brasserie",
      "BankAccount": "BE84 5679 9034 2356",
      "Address": "4, rue du marais 7030 Ghlin",
      "GetSalary": 3250.0,
      "Id": 4,
      "LastName": "Fritz",
      "FirstName": "Hector",
      "Gender": true,
      "Email": "fritzhector@gmail.com",
      "MobilePhoneNumber": null
    },
    {
      "$type": "Brasserie.Model.Restaurant.People.StaffMember, Brasserie",
      "BankAccount": "BE84 7090 3456 2390",
      "Address": "5, rue grande 7000 LosAngeles",
      "GetSalary": 32500.0,
      "Id": 5,
      "LastName": "Swift",
      "FirstName": "Taylor",
      "Gender": false,
      "Email": "taylor999@gmail.com",
      "MobilePhoneNumber": null
    },
    {
      "$type": "Brasserie.Model.Restaurant.People.StaffMember, Brasserie",
      "BankAccount": "BE90 3456 7892 2345",
      "Address": "203, rue des pres 7100 Soignies",
      "GetSalary": 2900.0,
      "Id": 6,
      "LastName": "Renard",
      "FirstName": "Fred",
      "Gender": true,
      "Email": "fredrenard01@gmail.com",
      "MobilePhoneNumber": null
    },
    {
      "$type": "Brasserie.Model.Restaurant.People.Manager, Brasserie",
      "Login": "TarneI",
      "BankAccount": "BE84 5454 6780 1243",
      "Address": "89, chemin vert 7030 Baudour",
      "GetSalary": 5234.0,
      "Id": 7,
      "LastName": "Tarne",
      "FirstName": "Isabelle",
      "Gender": false,
      "Email": "isablletarne@gmail.com",
      "MobilePhoneNumber": null
    }
  ]
}